zkitpg/__init__.py
zkit_pygame-1.0.0.0a0.dist-info/LICENSE
zkit_pygame-1.0.0.0a0.dist-info/METADATA
zkit_pygame-1.0.0.0a0.dist-info/WHEEL
zkit_pygame-1.0.0.0a0.dist-info/top_level.txt
zkit_pygame-1.0.0.0a0.dist-info/RECORD
